{
    "LANG_NAME": "ISPF Panel",
    "COMMENT_SINGLE": [],
    "COMMENT_MULTI": {
        "\/*": "*\/"
    },
    "CASE_KEYWORDS": 1,
    "QUOTEMARKS": [
        "'",
        "\""
    ],
    "ESCAPE_CHAR": "",
    "KEYWORDS": {
        "1": [
            ")CCSID",
            ")PANEL",
            ")ATTR",
            ")ABC",
            ")ABCINIT",
            ")ABCPROC",
            ")BODY",
            ")MODEL",
            ")AREA",
            ")INIT",
            ")REINIT",
            ")PROC",
            ")FIELD",
            ")HELP",
            ")LIST",
            ")PNTS",
            ")END"
        ],
        "2": [
            ")DEFAULT",
            ")BLANK",
            ")CM",
            ")DO",
            ")DOT",
            ")ELSE",
            ")ENDSEL",
            ")ENDDO",
            ")ENDDOT",
            ")IF",
            ")IM",
            ")ITERATE",
            ")LEAVE",
            ")NOP",
            ")SEL",
            ")SET",
            ")TB",
            ")TBA"
        ],
        "3": [
            ".ALARM",
            ".ATTR",
            ".ATTRCHAR",
            ".AUTOSEL",
            ".CSRPOS",
            ".CSRROW",
            ".CURSOR",
            ".HELP",
            ".HHELP",
            ".KANA",
            ".MSG",
            ".NRET",
            ".PFKEY",
            ".RESP",
            ".TRAIL",
            ".ZVARS"
        ],
        "4": [
            "WINDOW",
            "ALARM",
            "ATTN",
            "BARRIER",
            "HILITE",
            "CAPS",
            "CKBOX",
            "CLEAR",
            "CMD",
            "COLOR",
            "COMBO",
            "CSRGRP",
            "CUADYN",
            "SKIP",
            "INTENS",
            "AREA",
            "EXTEND",
            "DESC",
            "ASIS",
            "VGET",
            "VPUT",
            "JUST",
            "BATSCRD",
            "BATSCRW",
            "BDBCS",
            "BDISPMAX",
            "BIT",
            "BKGRND",
            "BREDIMAX",
            "PAD",
            "PADC",
            "PAS",
            "CHINESES",
            "CHINESET",
            "DANISH",
            "DATAMOD",
            "DDLIST",
            "DEPTH",
            "DUMP",
            "ENGLISH",
            "ERROR",
            "EXIT",
            "EXPAND",
            "FIELD",
            "FORMAT",
            "FRENCH",
            "GE",
            "GERMAN",
            "IMAGE",
            "IND",
            "TYPE",
            "ITALIAN",
            "JAPANESE",
            "KOREAN",
            "LCOL",
            "LEN",
            "LIND",
            "LISTBOX",
            "MODE",
            "NEST",
            "NOJUMP",
            "NOKANA",
            "NUMERIC",
            "OUTLINE",
            "PARM",
            "PGM",
            "PORTUGESE",
            "RADIO",
            "RCOL",
            "REP",
            "RIND",
            "ROWS",
            "SCALE",
            "SCROLL",
            "SFIHDR",
            "SGERMAN",
            "SIND",
            "SPANISH",
            "UPPERENG",
            "WIDTH"
        ],
        "5": [
            "ADDPOP",
            "ALPHA",
            "ALPHAB",
            "DYNAMIC",
            "SCRL",
            "CCSID",
            "COMMAND",
            "DSNAME",
            "DSNAMEF",
            "DSNAMEFM",
            "DSNAMEPQ",
            "DSNAMEQ",
            "EBCDIC",
            "ENBLDUMP",
            "ENUM",
            "FI",
            "FILEID",
            "FRAME",
            "GUI",
            "GUISCRD",
            "GUISCRW",
            "HEX",
            "HIGH",
            "IDATE",
            "IN",
            "INCLUDE",
            "INPUT",
            "ITIME",
            "JDATE",
            "JSTD",
            "KEYLIST",
            "LANG",
            "LEFT",
            "LIST",
            "LISTV",
            "LISTVX",
            "LISTX",
            "LMSG",
            "LOGO",
            "LOW",
            "MIX",
            "NAME",
            "NAMEF",
            "NB",
            "NEWAPPL",
            "NEWPOOL",
            "NOCHECK",
            "NOLOGO",
            "NON",
            "NONBLANK",
            "NULLS",
            "NUM",
            "OFF",
            "ON",
            "OPT",
            "OUT",
            "OUTPUT",
            "PANEL",
            "PICT",
            "PICTN",
            "POSITION",
            "TBDISPL",
            "PROFILE",
            "QUERY",
            "RANGE",
            "REVERSE",
            "RIGHT",
            "SHARED",
            "SMSG",
            "STDDATE",
            "STDTIME",
            "TERMSTAT",
            "TERMTRAC",
            "TEST",
            "TESTX",
            "TEXT",
            "TRACE",
            "TRACEX",
            "USCORE",
            "USER",
            "USERMOD",
            "WSCMD",
            "WSCMDV"
        ]
    },
    "SYMBOLS": [
        "(",
        ")",
        "=",
        "&",
        ",",
        "*",
        "#",
        "+",
        "&",
        "%",
        "_",
        "-",
        "@",
        "!"
    ],
    "CASE_SENSITIVE": [
        false,
        false,
        false,
        false,
        false,
        false
    ],
    "STYLES": {
        "BKGROUND": "background-color: #000000; color: #00FFFF;",
        "KEYWORDS": {
            "1": "color: #FF0000;",
            "2": "color: #21A502;",
            "3": "color: #FF00FF;",
            "4": "color: #876C00;",
            "5": "color: #00FF00;"
        },
        "COMMENTS": {
            "0": "color: #002EB8; font-style: italic;",
            "MULTI": "color: #002EB8; font-style: italic;"
        },
        "ESCAPE_CHAR": [
            ""
        ],
        "BRACKETS": [
            "color: #FF7400;"
        ],
        "STRINGS": [
            "color: #700000;"
        ],
        "NUMBERS": [
            "color: #FF6633;"
        ],
        "METHODS": {
            "1": "",
            "2": ""
        },
        "SYMBOLS": [
            "color: #FF7400;"
        ],
        "REGEXPS": [
            "color: #6B1F6B;"
        ],
        "SCRIPT": [
            ""
        ]
    },
    "URLS": {
        "1": "",
        "2": "",
        "3": "",
        "4": "",
        "5": ""
    },
    "OOLANG": false,
    "OBJECT_SPLITTERS": [],
    "REGEXPS": [
        "&amp;[a-zA-Z]{1,8}[0-9]{0,}"
    ],
    "STRICT_MODE_APPLIES": 0,
    "SCRIPT_DELIMITERS": [],
    "HIGHLIGHT_STRICT_BLOCK": []
}